emails/__init__.py
emails/admin.py
emails/apps.py
emails/backends.py
emails/celery.py
emails/models.py
emails/serializers.py
emails/signals.py
emails/strip.py
emails/tasks.py
emails/tests.py
emails/urls.py
emails/views.py
emails/migrations/0001_initial.py
emails/migrations/0002_usermodel.py
emails/migrations/0003_alter_usermodel_email.py
emails/migrations/0004_delete_usermodel.py
emails/migrations/0005_emailreminder_notifications_pushreminder.py
emails/migrations/0006_auto_20210819_0416.py
emails/migrations/0007_emailreminder_task.py
emails/migrations/0008_remove_emailreminder_task.py
emails/migrations/0009_policy.py
emails/migrations/0010_useremail.py
emails/migrations/0011_policies.py
emails/migrations/0012_useremails.py
emails/migrations/0013_auto_20210910_1029.py
emails/migrations/0014_delete_useremailing.py
emails/migrations/0015_delete_policy.py
emails/migrations/0016_delete_emailreminder.py
emails/migrations/0017_emailreminder_modules.py
emails/migrations/0018_delete_notify.py
emails/migrations/0019_list.py
emails/migrations/0020_emailreminder_date_time.py
emails/migrations/__init__.py
emails/templates/email.html
django_project_mailer-0.2.dist-info/METADATA
django_project_mailer-0.2.dist-info/WHEEL
django_project_mailer-0.2.dist-info/top_level.txt
django_project_mailer-0.2.dist-info/RECORD
