Metadata-Version: 2.1
Name: django-project-mailer
Version: 0.2
Summary: A Django app to conduct Web-based mailer.
Home-page: UNKNOWN
Author: Safana PB
Author-email: safna@gmail.com
License: BSD-3-Clause License
Platform: UNKNOWN
Classifier: Environment :: Web Environment
Classifier: Framework :: Django
Classifier: Framework :: Django :: 3.2
Classifier: Intended Audience :: Developers
Classifier: License :: OSI Approved :: BSD License
Classifier: Operating System :: OS Independent
Classifier: Programming Language :: Python
Classifier: Programming Language :: Python :: 3
Classifier: Programming Language :: Python :: 3 :: Only
Classifier: Programming Language :: Python :: 3.6
Classifier: Programming Language :: Python :: 3.7
Classifier: Programming Language :: Python :: 3.8
Classifier: Topic :: Internet :: WWW/HTTP
Classifier: Topic :: Internet :: WWW/HTTP :: Dynamic Content
Requires-Python: >=3.6
Requires-Dist: Django (>=2.2)
Requires-Dist: djangorestframework
Requires-Dist: django-celery-results
Requires-Dist: django-celery-beat
Requires-Dist: django-celery
Requires-Dist: Pillow
Requires-Dist: rabbitmq
Requires-Dist: redis
Requires-Dist: redis-server
